binlearn/__init__.py
binlearn/_pandas_config.py
binlearn/_polars_config.py
binlearn/_version.py
binlearn/config.py
binlearn/py.typed
binlearn/base/__init__.py
binlearn/base/_data_handling_base.py
binlearn/base/_flexible_binning_base.py
binlearn/base/_general_binning_base.py
binlearn/base/_interval_binning_base.py
binlearn/base/_sklearn_integration_base.py
binlearn/base/_supervised_binning_base.py
binlearn/base/_validation_mixin.py
binlearn/methods/__init__.py
binlearn/methods/_chi2_binning.py
binlearn/methods/_dbscan_binning.py
binlearn/methods/_equal_frequency_binning.py
binlearn/methods/_equal_width_binning.py
binlearn/methods/_equal_width_minimum_weight_binning.py
binlearn/methods/_gaussian_mixture_binning.py
binlearn/methods/_isotonic_binning.py
binlearn/methods/_kmeans_binning.py
binlearn/methods/_manual_flexible_binning.py
binlearn/methods/_manual_interval_binning.py
binlearn/methods/_singleton_binning.py
binlearn/methods/_tree_binning.py
binlearn/tools/__init__.py
binlearn/tools/_sklearn.py
binlearn/utils/__init__.py
binlearn/utils/_binning_operations.py
binlearn/utils/_configuration_utils.py
binlearn/utils/_data_handling.py
binlearn/utils/_equal_width_utils.py
binlearn/utils/_error_handling.py
binlearn/utils/_errors.py
binlearn/utils/_parameter_validation.py
binlearn/utils/_types.py
binlearn/utils/_validation.py
binlearn-1.0.1.dist-info/licenses/LICENSE
binlearn-1.0.1.dist-info/METADATA
binlearn-1.0.1.dist-info/WHEEL
binlearn-1.0.1.dist-info/top_level.txt
binlearn-1.0.1.dist-info/RECORD
