Metadata-Version: 2.4
Name: binlearn
Version: 1.0.1
Summary: A comprehensive binning and discretization library for machine learning
Author-email: The DAALAB <gyorgy.kovacs@daalab.com>
Maintainer-email: The DAALAB <gyorgy.kovacs@daalab.com>
License-Expression: MIT
Project-URL: Homepage, https://github.com/TheDAALab/binlearn
Project-URL: Documentation, https://binlearn.readthedocs.io/
Project-URL: Repository, https://github.com/TheDAALab/binlearn.git
Project-URL: Bug Tracker, https://github.com/TheDAALab/binlearn/issues
Project-URL: Changelog, https://github.com/TheDAALab/binlearn/blob/main/CHANGELOG.md
Keywords: binning,discretization,binlearn,data preprocessing,machine learning,data science,feature engineering
Classifier: Development Status :: 5 - Production/Stable
Classifier: Intended Audience :: Science/Research
Classifier: Intended Audience :: Developers
Classifier: Programming Language :: Python
Classifier: Programming Language :: Python :: 3
Classifier: Programming Language :: Python :: 3.10
Classifier: Programming Language :: Python :: 3.11
Classifier: Programming Language :: Python :: 3.12
Classifier: Programming Language :: Python :: 3.13
Classifier: Topic :: Scientific/Engineering :: Artificial Intelligence
Classifier: Topic :: Software Development
Classifier: Topic :: Software Development :: Libraries :: Python Modules
Classifier: Operating System :: Microsoft :: Windows
Classifier: Operating System :: POSIX
Classifier: Operating System :: Unix
Classifier: Operating System :: MacOS
Requires-Python: >=3.10
License-File: LICENSE
Requires-Dist: numpy>=1.21.0
Requires-Dist: scipy>=1.7.0
Requires-Dist: kmeans1d>=0.3.0
Requires-Dist: scikit-learn>=1.0.0
Provides-Extra: tests
Requires-Dist: pytest>=6.0; extra == "tests"
Requires-Dist: pytest-cov>=2.10; extra == "tests"
Requires-Dist: pytest-xdist>=2.0; extra == "tests"
Requires-Dist: ruff>=0.1.0; extra == "tests"
Requires-Dist: mypy>=1.0.0; extra == "tests"
Provides-Extra: docs
Requires-Dist: sphinx>=4.0; extra == "docs"
Requires-Dist: sphinx-rtd-theme>=1.0; extra == "docs"
Requires-Dist: myst-parser>=0.18; extra == "docs"
Requires-Dist: sphinx-autodoc-typehints>=1.12; extra == "docs"
Provides-Extra: dev
Requires-Dist: black>=22.0; extra == "dev"
Requires-Dist: isort>=5.10; extra == "dev"
Requires-Dist: flake8>=4.0; extra == "dev"
Requires-Dist: pylint>=2.15.0; extra == "dev"
Requires-Dist: mypy>=0.910; extra == "dev"
Requires-Dist: pre-commit>=2.15; extra == "dev"
Requires-Dist: build>=0.8; extra == "dev"
Requires-Dist: twine>=4.0; extra == "dev"
Requires-Dist: setuptools_scm>=8.0; extra == "dev"
Requires-Dist: ruff>=0.1.0; extra == "dev"
Provides-Extra: pandas
Requires-Dist: pandas>=1.3.0; extra == "pandas"
Provides-Extra: polars
Requires-Dist: polars>=0.15.0; extra == "polars"
Provides-Extra: all
Requires-Dist: binlearn[dev,docs,pandas,polars,tests]; extra == "all"
Dynamic: license-file
